{"@type":"Flow","@id":"7ae3bfc5-8532-11e0-9d78-0800200c9a66","name":"Wood, soft, US PNW, standing/m3","category":"Elementary flows/Resource/biotic","version":"01.00.000","lastChange":"2014-06-19T15:39:13.774Z","flowType":"ELEMENTARY_FLOW","isInfrastructureFlow":false,"flowProperties":[{"@type":"FlowPropertyFactor","isRefFlowProperty":true,"flowProperty":{"@type":"FlowProperty","@id":"93a60a56-a3c8-22da-a746-0800200c9a66","name":"Volume","category":"Technical flow properties","refUnit":"m3"},"conversionFactor":1.0}]}