{"@type":"Flow","@id":"e4366527-6df5-47bc-80d3-398d2947619b","name":"Phenol, 2,4-dichloro-, sodium salt","category":"Elementary flows/Emission to soil/unspecified","version":"01.00.000","lastChange":"2014-06-19T15:39:19.833Z","flowType":"ELEMENTARY_FLOW","cas":"003757-76-4","isInfrastructureFlow":false,"flowProperties":[{"@type":"FlowPropertyFactor","isRefFlowProperty":true,"flowProperty":{"@type":"FlowProperty","@id":"93a60a56-a3c8-11da-a746-0800200b9a66","name":"Mass","category":"Technical flow properties","refUnit":"kg"},"conversionFactor":1.0}]}