{"@type":"Flow","@id":"ae1a102d-ad57-4062-9166-7b421bc5f2c0","name":"Terbufos","category":"Elementary flows/Emission to water/ocean","version":"01.00.000","lastChange":"2014-06-19T15:39:14.133Z","flowType":"ELEMENTARY_FLOW","cas":"013071-79-9","formula":"C9H21O2PS3","isInfrastructureFlow":false,"flowProperties":[{"@type":"FlowPropertyFactor","isRefFlowProperty":true,"flowProperty":{"@type":"FlowProperty","@id":"93a60a56-a3c8-11da-a746-0800200b9a66","name":"Mass","category":"Technical flow properties","refUnit":"kg"},"conversionFactor":1.0}]}