{"@type":"Flow","@id":"20bc9500-2e2f-4cba-9332-8ea17d362aba","name":"Bromine","category":"Elementary flows/Emission to water/ground water, long-term","version":"01.00.000","lastChange":"2014-06-19T15:39:15.680Z","flowType":"ELEMENTARY_FLOW","cas":"007726-95-6","formula":"Br","isInfrastructureFlow":false,"flowProperties":[{"@type":"FlowPropertyFactor","isRefFlowProperty":true,"flowProperty":{"@type":"FlowProperty","@id":"93a60a56-a3c8-11da-a746-0800200b9a66","name":"Mass","category":"Technical flow properties","refUnit":"kg"},"conversionFactor":1.0}]}