{"@type":"Flow","@id":"9e4ec852-d3bb-4bad-9696-50601889648c","name":"Methyl methacrylate","category":"Elementary flows/Emission to water/fresh water, long-term","version":"01.00.000","lastChange":"2014-06-19T15:39:15.482Z","flowType":"ELEMENTARY_FLOW","cas":"000080-62-6","isInfrastructureFlow":false,"flowProperties":[{"@type":"FlowPropertyFactor","isRefFlowProperty":true,"flowProperty":{"@type":"FlowProperty","@id":"93a60a56-a3c8-11da-a746-0800200b9a66","name":"Mass","category":"Technical flow properties","refUnit":"kg"},"conversionFactor":1.0}]}