{"@type":"Flow","@id":"011403fa-9fb9-4d0d-a2e7-4307c64dae44","name":"Methyl formate","category":"Elementary flows/Emission to water/river, long-term","version":"01.00.000","lastChange":"2014-06-19T15:39:14.514Z","flowType":"ELEMENTARY_FLOW","cas":"000107-31-3","isInfrastructureFlow":false,"flowProperties":[{"@type":"FlowPropertyFactor","isRefFlowProperty":true,"flowProperty":{"@type":"FlowProperty","@id":"93a60a56-a3c8-11da-a746-0800200b9a66","name":"Mass","category":"Technical flow properties","refUnit":"kg"},"conversionFactor":1.0}]}