{"@type":"Flow","@id":"7ca6314d-4ca2-49ab-b1a5-83811a3a9b1f","name":"Molybdenum-99","category":"Elementary flows/Emission to water/fresh water","version":"01.00.000","lastChange":"2014-06-19T15:39:14.321Z","flowType":"ELEMENTARY_FLOW","cas":"014119-15-4","formula":"Mo-99","isInfrastructureFlow":false,"flowProperties":[{"@type":"FlowPropertyFactor","isRefFlowProperty":true,"flowProperty":{"@type":"FlowProperty","@id":"93a60a56-a3c8-17da-a746-0800200c9a66","name":"Radioactivity","category":"Technical flow properties","refUnit":"kBq"},"conversionFactor":1.0}]}