{"@type":"Flow","@id":"31d59458-9ada-447c-9c18-4c28127695b7","name":"Metaldehyde (tetramer)","category":"Elementary flows/Emission to soil/industrial","version":"01.00.000","lastChange":"2014-06-19T15:39:18.351Z","flowType":"ELEMENTARY_FLOW","cas":"000108-62-3","formula":"C8H16O4","isInfrastructureFlow":false,"flowProperties":[{"@type":"FlowPropertyFactor","isRefFlowProperty":true,"flowProperty":{"@type":"FlowProperty","@id":"93a60a56-a3c8-11da-a746-0800200b9a66","name":"Mass","category":"Technical flow properties","refUnit":"kg"},"conversionFactor":1.0}]}