{"@type":"Flow","@id":"8dbe8ad6-b351-464a-aa7f-b6c7c66d5b14","name":"Thifensulfuron-methyl","category":"Elementary flows/Emission to soil/industrial","version":"01.00.000","lastChange":"2014-06-19T15:39:18.352Z","flowType":"ELEMENTARY_FLOW","cas":"079277-27-3","formula":"C12H13N5O6S2","isInfrastructureFlow":false,"flowProperties":[{"@type":"FlowPropertyFactor","isRefFlowProperty":true,"flowProperty":{"@type":"FlowProperty","@id":"93a60a56-a3c8-11da-a746-0800200b9a66","name":"Mass","category":"Technical flow properties","refUnit":"kg"},"conversionFactor":1.0}]}