{"@type":"Flow","@id":"f1df0c48-8e1a-4df9-a7b5-f6ac71df426d","name":"m-Xylene","category":"Elementary flows/Emission to soil/industrial","version":"01.00.000","lastChange":"2014-06-19T15:39:18.352Z","flowType":"ELEMENTARY_FLOW","cas":"000108-38-3","formula":"C6H4(CH3)2","isInfrastructureFlow":false,"flowProperties":[{"@type":"FlowPropertyFactor","isRefFlowProperty":true,"flowProperty":{"@type":"FlowProperty","@id":"93a60a56-a3c8-11da-a746-0800200b9a66","name":"Mass","category":"Technical flow properties","refUnit":"kg"},"conversionFactor":1.0}]}